nefile/Exceptions.py
nefile/__init__.py
nefile/nefile.py
nefile/resource_table.py
nefile/resources/__init__.py
nefile/resources/application_defined_data.py
nefile/resources/bitmap.py
nefile/resources/cursor.py
nefile/resources/icon.py
nefile/resources/string.py
nefile-0.9.2.dist-info/LICENSE
nefile-0.9.2.dist-info/METADATA
nefile-0.9.2.dist-info/WHEEL
nefile-0.9.2.dist-info/top_level.txt
nefile-0.9.2.dist-info/RECORD
