Metadata-Version: 2.1
Name: nefile
Version: 0.9.2
Summary: Parse 16-bit New Executable (NE) programs.
Author: npjg
License: MIT License
Project-URL: Homepage, https://github.com/npjg/nefile
Keywords: struct,reverse-engineering
Classifier: License :: OSI Approved :: MIT License
Classifier: Programming Language :: Python
Classifier: Programming Language :: Python :: 3
Requires-Python: >=3.9
License-File: LICENSE
Requires-Dist: self-documenting-struct >=0.9.1
